__version__.py
rfb_cycler_datatypes/comm_data/__init__.py
rfb_cycler_datatypes/comm_data/comm_data.py
rfb_cycler_datatypes/cycler_data/__init__.py
rfb_cycler_datatypes/cycler_data/cycler_data_battery.py
rfb_cycler_datatypes/cycler_data/cycler_data_common.py
rfb_cycler_datatypes/cycler_data/cycler_data_device.py
rfb_cycler_datatypes/cycler_data/cycler_data_experiment.py
rfb_cycler_datatypes-0.0.1.dist-info/LICENSE.txt
rfb_cycler_datatypes-0.0.1.dist-info/METADATA
rfb_cycler_datatypes-0.0.1.dist-info/WHEEL
rfb_cycler_datatypes-0.0.1.dist-info/top_level.txt
rfb_cycler_datatypes-0.0.1.dist-info/RECORD
